<?xml version="1.0" ?>
<!--动画帧信息表-->
<animation>
    <action totalFrame="12" actionName="bullet_1_0">
        <frameInfo frame="0">
            <frameData bitmapName="bullet_1" scaleX="-1.000000" scaleY="-1.000000" rotation="179.999985" position="-0.150000,47.799999" />
        </frameInfo>
        <frameInfo frame="1">
            <frameData bitmapName="bullet_1" scaleX="-1.000000" scaleY="-1.000000" rotation="179.999985" position="-0.150000,47.799999" />
        </frameInfo>
        <frameInfo frame="2">
            <frameData bitmapName="bullet_1" scaleX="-1.000000" scaleY="-1.000000" rotation="179.999985" position="-0.150000,47.799999" />
        </frameInfo>
        <frameInfo frame="3">
            <frameData bitmapName="bullet_1" scaleX="-1.000000" scaleY="-1.000000" rotation="179.999985" position="-0.150000,47.799999" />
        </frameInfo>
        <frameInfo frame="4">
            <frameData bitmapName="bullet_1" scaleX="-1.000000" scaleY="-1.000000" rotation="179.999985" position="-0.150000,47.799999" />
        </frameInfo>
        <frameInfo frame="5">
            <frameData bitmapName="bullet_1" scaleX="-1.000000" scaleY="-1.000000" rotation="179.999985" position="-0.150000,47.799999" />
        </frameInfo>
        <frameInfo frame="6">
            <frameData bitmapName="bullet_1" scaleX="-1.000000" scaleY="-1.000000" rotation="179.999985" position="-0.150000,47.799999" />
        </frameInfo>
        <frameInfo frame="7">
            <frameData bitmapName="bullet_1" scaleX="-1.000000" scaleY="-1.000000" rotation="179.999985" position="-0.150000,47.799999" />
        </frameInfo>
        <frameInfo frame="8">
            <frameData bitmapName="bullet_1" scaleX="-1.000000" scaleY="-1.000000" rotation="179.999985" position="-0.150000,47.799999" />
        </frameInfo>
        <frameInfo frame="9">
            <frameData bitmapName="bullet_1" scaleX="-1.000000" scaleY="-1.000000" rotation="179.999985" position="-0.150000,47.799999" />
        </frameInfo>
        <frameInfo frame="10">
            <frameData bitmapName="bullet_1" scaleX="-1.000000" scaleY="-1.000000" rotation="179.999985" position="-0.150000,47.799999" />
        </frameInfo>
        <frameInfo frame="11">
            <frameData bitmapName="bullet_1" scaleX="-1.000000" scaleY="-1.000000" rotation="179.999985" position="-0.150000,47.799999" />
        </frameInfo>
    </action>
</animation>
